__init__.py
ppbar.py
parallel_progress_bar-0.2.0.dist-info/LICENSE
parallel_progress_bar-0.2.0.dist-info/METADATA
parallel_progress_bar-0.2.0.dist-info/WHEEL
parallel_progress_bar-0.2.0.dist-info/entry_points.txt
parallel_progress_bar-0.2.0.dist-info/top_level.txt
parallel_progress_bar-0.2.0.dist-info/RECORD
