Metadata-Version: 2.2
Name: parallel-progress-bar
Version: 0.2.0
Summary: slim gnu-parallel clone with a better progress bar
Author-email: Asher Mancinelli <ashermancinelli@gmail.com>
License: MIT License
Classifier: Programming Language :: Python :: 3
Classifier: License :: OSI Approved :: MIT License
Classifier: Operating System :: OS Independent
Requires-Python: >=3.7
License-File: LICENSE
Requires-Dist: tqdm
